CHANGES.txt
MANIFEST.in
README.txt
setup.py
src/rsl/__init__.py
src/rsl.jsonrpc10.egg-info/PKG-INFO
src/rsl.jsonrpc10.egg-info/SOURCES.txt
src/rsl.jsonrpc10.egg-info/dependency_links.txt
src/rsl.jsonrpc10.egg-info/entry_points.txt
src/rsl.jsonrpc10.egg-info/namespace_packages.txt
src/rsl.jsonrpc10.egg-info/requires.txt
src/rsl.jsonrpc10.egg-info/top_level.txt
src/rsl/jsonrpc10/__init__.py
src/rsl/jsonrpc10/descr.py
src/rsl/jsonrpc10/factories.py
src/rsl/jsonrpc10/proxy.py
src/rsl/jsonrpc10/serializer.py